{
    "balanced_accuracy": 0.8071099407504938,
    "accuracy": 0.8108108108108109,
    "log_loss": 0.47237566611219206,
    "roc_auc": 0.8071099407504937,
    "f1": 0.7835051546391752,
    "precision": 0.7916666666666666,
    "recall": 0.7755102040816326,
    "training_time": 0.04530739784240723,
    "inference_time": 0.0006844997406005859,
    "dataset": "australian",
    "model": "xgboost",
    "fold": "F1",
    "architecture_name": "A2",
    "fs_method": "random_4",
    "fs_percent": 0.6,
    "fs_n_features": 8
}