{"train_loss": 0.712711220810132, "valid_loss": 0.7009523437174666, "balanced_accuracy": 0.5, "accuracy": 0.4882943143812709, "roc_auc": 0.5, "f1": 0.0, "recall": 0.0, "time_this_iter_s": 3.9745147228240967, "done": false, "timesteps_total": null, "episodes_total": null, "training_iteration": 1, "trial_id": "74e92bae", "experiment_id": "8fc8bd7f408f43408fe95052fcbed156", "date": "2022-02-28_21-58-27", "timestamp": 1646107107, "time_total_s": 3.9745147228240967, "pid": 10361, "hostname": "uriel", "node_ip": "192.168.1.72", "config": {"n_layers": 2, "optimizer__lr": 0.02557053217832841, "n_head": 32, "n_hid": 256, "dropout": 0.2524905611969797}, "time_since_restore": 3.9745147228240967, "timesteps_since_restore": 0, "iterations_since_restore": 1}
{"train_loss": 0.6981755615729598, "valid_loss": 0.6999655406311603, "balanced_accuracy": 0.5, "accuracy": 0.4882943143812709, "roc_auc": 0.5, "f1": 0.0, "recall": 0.0, "time_this_iter_s": 1.895097255706787, "done": false, "timesteps_total": null, "episodes_total": null, "training_iteration": 2, "trial_id": "74e92bae", "experiment_id": "8fc8bd7f408f43408fe95052fcbed156", "date": "2022-02-28_21-58-29", "timestamp": 1646107109, "time_total_s": 5.869611978530884, "pid": 10361, "hostname": "uriel", "node_ip": "192.168.1.72", "config": {"n_layers": 2, "optimizer__lr": 0.02557053217832841, "n_head": 32, "n_hid": 256, "dropout": 0.2524905611969797}, "time_since_restore": 5.869611978530884, "timesteps_since_restore": 0, "iterations_since_restore": 2}
{"train_loss": 0.6956619116550269, "valid_loss": 0.7006047173686649, "balanced_accuracy": 0.5, "accuracy": 0.4882943143812709, "roc_auc": 0.5, "f1": 0.0, "recall": 0.0, "time_this_iter_s": 1.8745450973510742, "done": false, "timesteps_total": null, "episodes_total": null, "training_iteration": 3, "trial_id": "74e92bae", "experiment_id": "8fc8bd7f408f43408fe95052fcbed156", "date": "2022-02-28_21-58-31", "timestamp": 1646107111, "time_total_s": 7.744157075881958, "pid": 10361, "hostname": "uriel", "node_ip": "192.168.1.72", "config": {"n_layers": 2, "optimizer__lr": 0.02557053217832841, "n_head": 32, "n_hid": 256, "dropout": 0.2524905611969797}, "time_since_restore": 7.744157075881958, "timesteps_since_restore": 0, "iterations_since_restore": 3}
{"train_loss": 0.6995529875921184, "valid_loss": 0.7006888235592125, "balanced_accuracy": 0.5, "accuracy": 0.4882943143812709, "roc_auc": 0.5, "f1": 0.0, "recall": 0.0, "time_this_iter_s": 1.8694300651550293, "done": false, "timesteps_total": null, "episodes_total": null, "training_iteration": 4, "trial_id": "74e92bae", "experiment_id": "8fc8bd7f408f43408fe95052fcbed156", "date": "2022-02-28_21-58-33", "timestamp": 1646107113, "time_total_s": 9.613587141036987, "pid": 10361, "hostname": "uriel", "node_ip": "192.168.1.72", "config": {"n_layers": 2, "optimizer__lr": 0.02557053217832841, "n_head": 32, "n_hid": 256, "dropout": 0.2524905611969797}, "time_since_restore": 9.613587141036987, "timesteps_since_restore": 0, "iterations_since_restore": 4}
{"train_loss": 0.697601390378011, "valid_loss": 0.7000958613528057, "balanced_accuracy": 0.5, "accuracy": 0.4882943143812709, "roc_auc": 0.5, "f1": 0.0, "recall": 0.0, "time_this_iter_s": 1.8609914779663086, "done": false, "timesteps_total": null, "episodes_total": null, "training_iteration": 5, "trial_id": "74e92bae", "experiment_id": "8fc8bd7f408f43408fe95052fcbed156", "date": "2022-02-28_21-58-35", "timestamp": 1646107115, "time_total_s": 11.474578619003296, "pid": 10361, "hostname": "uriel", "node_ip": "192.168.1.72", "config": {"n_layers": 2, "optimizer__lr": 0.02557053217832841, "n_head": 32, "n_hid": 256, "dropout": 0.2524905611969797}, "time_since_restore": 11.474578619003296, "timesteps_since_restore": 0, "iterations_since_restore": 5}
{"train_loss": 0.6954924662762196, "valid_loss": 0.6984513395506403, "balanced_accuracy": 0.5, "accuracy": 0.4882943143812709, "roc_auc": 0.5, "f1": 0.0, "recall": 0.0, "time_this_iter_s": 1.8629341125488281, "done": false, "timesteps_total": null, "episodes_total": null, "training_iteration": 6, "trial_id": "74e92bae", "experiment_id": "8fc8bd7f408f43408fe95052fcbed156", "date": "2022-02-28_21-58-37", "timestamp": 1646107117, "time_total_s": 13.337512731552124, "pid": 10361, "hostname": "uriel", "node_ip": "192.168.1.72", "config": {"n_layers": 2, "optimizer__lr": 0.02557053217832841, "n_head": 32, "n_hid": 256, "dropout": 0.2524905611969797}, "time_since_restore": 13.337512731552124, "timesteps_since_restore": 0, "iterations_since_restore": 6}
{"train_loss": 0.6966417987439828, "valid_loss": 0.6995774362497904, "balanced_accuracy": 0.5, "accuracy": 0.4882943143812709, "roc_auc": 0.5, "f1": 0.0, "recall": 0.0, "time_this_iter_s": 1.8561615943908691, "done": false, "timesteps_total": null, "episodes_total": null, "training_iteration": 7, "trial_id": "74e92bae", "experiment_id": "8fc8bd7f408f43408fe95052fcbed156", "date": "2022-02-28_21-58-38", "timestamp": 1646107118, "time_total_s": 15.193674325942993, "pid": 10361, "hostname": "uriel", "node_ip": "192.168.1.72", "config": {"n_layers": 2, "optimizer__lr": 0.02557053217832841, "n_head": 32, "n_hid": 256, "dropout": 0.2524905611969797}, "time_since_restore": 15.193674325942993, "timesteps_since_restore": 0, "iterations_since_restore": 7}
{"train_loss": 0.697577007013402, "valid_loss": 0.6994960970404156, "balanced_accuracy": 0.5, "accuracy": 0.4882943143812709, "roc_auc": 0.5, "f1": 0.0, "recall": 0.0, "time_this_iter_s": 1.862670660018921, "done": false, "timesteps_total": null, "episodes_total": null, "training_iteration": 8, "trial_id": "74e92bae", "experiment_id": "8fc8bd7f408f43408fe95052fcbed156", "date": "2022-02-28_21-58-40", "timestamp": 1646107120, "time_total_s": 17.056344985961914, "pid": 10361, "hostname": "uriel", "node_ip": "192.168.1.72", "config": {"n_layers": 2, "optimizer__lr": 0.02557053217832841, "n_head": 32, "n_hid": 256, "dropout": 0.2524905611969797}, "time_since_restore": 17.056344985961914, "timesteps_since_restore": 0, "iterations_since_restore": 8}
{"train_loss": 0.6958626388085808, "valid_loss": 0.6995313506959673, "balanced_accuracy": 0.5, "accuracy": 0.4882943143812709, "roc_auc": 0.5, "f1": 0.0, "recall": 0.0, "time_this_iter_s": 1.9285659790039062, "done": false, "timesteps_total": null, "episodes_total": null, "training_iteration": 9, "trial_id": "74e92bae", "experiment_id": "8fc8bd7f408f43408fe95052fcbed156", "date": "2022-02-28_21-58-42", "timestamp": 1646107122, "time_total_s": 18.98491096496582, "pid": 10361, "hostname": "uriel", "node_ip": "192.168.1.72", "config": {"n_layers": 2, "optimizer__lr": 0.02557053217832841, "n_head": 32, "n_hid": 256, "dropout": 0.2524905611969797}, "time_since_restore": 18.98491096496582, "timesteps_since_restore": 0, "iterations_since_restore": 9}
{"train_loss": 0.6966159171616066, "valid_loss": 0.6987544071913563, "balanced_accuracy": 0.5, "accuracy": 0.4882943143812709, "roc_auc": 0.5, "f1": 0.0, "recall": 0.0, "time_this_iter_s": 1.8719003200531006, "done": false, "timesteps_total": null, "episodes_total": null, "training_iteration": 10, "trial_id": "74e92bae", "experiment_id": "8fc8bd7f408f43408fe95052fcbed156", "date": "2022-02-28_21-58-44", "timestamp": 1646107124, "time_total_s": 20.85681128501892, "pid": 10361, "hostname": "uriel", "node_ip": "192.168.1.72", "config": {"n_layers": 2, "optimizer__lr": 0.02557053217832841, "n_head": 32, "n_hid": 256, "dropout": 0.2524905611969797}, "time_since_restore": 20.85681128501892, "timesteps_since_restore": 0, "iterations_since_restore": 10}
{"train_loss": 0.697524311679844, "valid_loss": 0.6987861004162792, "balanced_accuracy": 0.5, "accuracy": 0.4882943143812709, "roc_auc": 0.5, "f1": 0.0, "recall": 0.0, "time_this_iter_s": 1.8725733757019043, "done": false, "timesteps_total": null, "episodes_total": null, "training_iteration": 11, "trial_id": "74e92bae", "experiment_id": "8fc8bd7f408f43408fe95052fcbed156", "date": "2022-02-28_21-58-46", "timestamp": 1646107126, "time_total_s": 22.729384660720825, "pid": 10361, "hostname": "uriel", "node_ip": "192.168.1.72", "config": {"n_layers": 2, "optimizer__lr": 0.02557053217832841, "n_head": 32, "n_hid": 256, "dropout": 0.2524905611969797}, "time_since_restore": 22.729384660720825, "timesteps_since_restore": 0, "iterations_since_restore": 11}
{"train_loss": 0.6974713478708907, "valid_loss": 0.6979683038084005, "balanced_accuracy": 0.5, "accuracy": 0.4882943143812709, "roc_auc": 0.5, "f1": 0.0, "recall": 0.0, "time_this_iter_s": 1.8920176029205322, "done": false, "timesteps_total": null, "episodes_total": null, "training_iteration": 12, "trial_id": "74e92bae", "experiment_id": "8fc8bd7f408f43408fe95052fcbed156", "date": "2022-02-28_21-58-48", "timestamp": 1646107128, "time_total_s": 24.621402263641357, "pid": 10361, "hostname": "uriel", "node_ip": "192.168.1.72", "config": {"n_layers": 2, "optimizer__lr": 0.02557053217832841, "n_head": 32, "n_hid": 256, "dropout": 0.2524905611969797}, "time_since_restore": 24.621402263641357, "timesteps_since_restore": 0, "iterations_since_restore": 12}
{"train_loss": 0.6964438023624906, "valid_loss": 0.698150875975057, "balanced_accuracy": 0.5, "accuracy": 0.4882943143812709, "roc_auc": 0.5, "f1": 0.0, "recall": 0.0, "time_this_iter_s": 1.8803281784057617, "done": false, "timesteps_total": null, "episodes_total": null, "training_iteration": 13, "trial_id": "74e92bae", "experiment_id": "8fc8bd7f408f43408fe95052fcbed156", "date": "2022-02-28_21-58-50", "timestamp": 1646107130, "time_total_s": 26.50173044204712, "pid": 10361, "hostname": "uriel", "node_ip": "192.168.1.72", "config": {"n_layers": 2, "optimizer__lr": 0.02557053217832841, "n_head": 32, "n_hid": 256, "dropout": 0.2524905611969797}, "time_since_restore": 26.50173044204712, "timesteps_since_restore": 0, "iterations_since_restore": 13}
{"train_loss": 0.6958581425845998, "valid_loss": 0.6980814267460718, "balanced_accuracy": 0.5, "accuracy": 0.4882943143812709, "roc_auc": 0.5, "f1": 0.0, "recall": 0.0, "time_this_iter_s": 1.9809167385101318, "done": false, "timesteps_total": null, "episodes_total": null, "training_iteration": 14, "trial_id": "74e92bae", "experiment_id": "8fc8bd7f408f43408fe95052fcbed156", "date": "2022-02-28_21-58-52", "timestamp": 1646107132, "time_total_s": 28.48264718055725, "pid": 10361, "hostname": "uriel", "node_ip": "192.168.1.72", "config": {"n_layers": 2, "optimizer__lr": 0.02557053217832841, "n_head": 32, "n_hid": 256, "dropout": 0.2524905611969797}, "time_since_restore": 28.48264718055725, "timesteps_since_restore": 0, "iterations_since_restore": 14}
{"train_loss": 0.6958185672675699, "valid_loss": 0.6985396673049417, "balanced_accuracy": 0.5, "accuracy": 0.4882943143812709, "roc_auc": 0.5, "f1": 0.0, "recall": 0.0, "time_this_iter_s": 1.9266517162322998, "done": true, "timesteps_total": null, "episodes_total": null, "training_iteration": 15, "trial_id": "74e92bae", "experiment_id": "8fc8bd7f408f43408fe95052fcbed156", "date": "2022-02-28_21-58-54", "timestamp": 1646107134, "time_total_s": 30.40929889678955, "pid": 10361, "hostname": "uriel", "node_ip": "192.168.1.72", "config": {"n_layers": 2, "optimizer__lr": 0.02557053217832841, "n_head": 32, "n_hid": 256, "dropout": 0.2524905611969797}, "time_since_restore": 30.40929889678955, "timesteps_since_restore": 0, "iterations_since_restore": 15}
