{
    "balanced_accuracy": 0.9309810290101129,
    "accuracy": 0.9474066013783098,
    "log_loss": 0.13284533690796566,
    "roc_auc": 0.9309810290101129,
    "f1": 0.9633653360282971,
    "precision": 0.957318604067286,
    "recall": 0.969488939740656,
    "training_time": 86.62670588493347,
    "inference_time": 0.10365843772888184,
    "dataset": "nomao",
    "model": "mlp/full_nd_nn",
    "fold": "F2",
    "architecture_name": "A0",
    "fs_method": "none",
    "fs_percent": 1.0,
    "fs_n_features": 118
}