{"train_loss": 2.40514873697618, "valid_loss": 2.3936557064035573, "balanced_accuracy": 0.0698026323927735, "accuracy": 0.02426301103967002, "time_this_iter_s": 15.867936611175537, "done": false, "timesteps_total": null, "episodes_total": null, "training_iteration": 1, "trial_id": "a0875632", "experiment_id": "ba764abc1df047249af424415e270160", "date": "2022-07-12_18-02-13", "timestamp": 1657666933, "time_total_s": 15.867936611175537, "pid": 205749, "hostname": "desktop", "node_ip": "127.0.1.1", "config": {"n_layers": 2, "optimizer__lr": 3.056740793738313e-05, "n_head": 8, "n_hid": 64, "dropout": 0.048264643591270306, "numerical_passthrough": true}, "time_since_restore": 15.867936611175537, "timesteps_since_restore": 0, "iterations_since_restore": 1}
{"train_loss": 2.383101019222413, "valid_loss": 2.3716651816601226, "balanced_accuracy": 0.09230399755160511, "accuracy": 0.23256096081523717, "time_this_iter_s": 13.108681201934814, "done": false, "timesteps_total": null, "episodes_total": null, "training_iteration": 2, "trial_id": "a0875632", "experiment_id": "ba764abc1df047249af424415e270160", "date": "2022-07-12_18-02-26", "timestamp": 1657666946, "time_total_s": 28.97661781311035, "pid": 205749, "hostname": "desktop", "node_ip": "127.0.1.1", "config": {"n_layers": 2, "optimizer__lr": 3.056740793738313e-05, "n_head": 8, "n_hid": 64, "dropout": 0.048264643591270306, "numerical_passthrough": true}, "time_since_restore": 28.97661781311035, "timesteps_since_restore": 0, "iterations_since_restore": 2}
{"train_loss": 2.36166680025473, "valid_loss": 2.350246085366274, "balanced_accuracy": 0.09089399198664129, "accuracy": 0.3293097173359214, "time_this_iter_s": 11.939410924911499, "done": false, "timesteps_total": null, "episodes_total": null, "training_iteration": 3, "trial_id": "a0875632", "experiment_id": "ba764abc1df047249af424415e270160", "date": "2022-07-12_18-02-38", "timestamp": 1657666958, "time_total_s": 40.91602873802185, "pid": 205749, "hostname": "desktop", "node_ip": "127.0.1.1", "config": {"n_layers": 2, "optimizer__lr": 3.056740793738313e-05, "n_head": 8, "n_hid": 64, "dropout": 0.048264643591270306, "numerical_passthrough": true}, "time_since_restore": 40.91602873802185, "timesteps_since_restore": 0, "iterations_since_restore": 3}
{"train_loss": 2.340718439622338, "valid_loss": 2.32928745613274, "balanced_accuracy": 0.09090909090909091, "accuracy": 0.32955234744631806, "time_this_iter_s": 14.146728038787842, "done": false, "timesteps_total": null, "episodes_total": null, "training_iteration": 4, "trial_id": "a0875632", "experiment_id": "ba764abc1df047249af424415e270160", "date": "2022-07-12_18-02-52", "timestamp": 1657666972, "time_total_s": 55.06275677680969, "pid": 205749, "hostname": "desktop", "node_ip": "127.0.1.1", "config": {"n_layers": 2, "optimizer__lr": 3.056740793738313e-05, "n_head": 8, "n_hid": 64, "dropout": 0.048264643591270306, "numerical_passthrough": true}, "time_since_restore": 55.06275677680969, "timesteps_since_restore": 0, "iterations_since_restore": 4}
{"train_loss": 2.3202247232918194, "valid_loss": 2.3087057961750044, "balanced_accuracy": 0.09090909090909091, "accuracy": 0.32955234744631806, "time_this_iter_s": 12.94313669204712, "done": false, "timesteps_total": null, "episodes_total": null, "training_iteration": 5, "trial_id": "a0875632", "experiment_id": "ba764abc1df047249af424415e270160", "date": "2022-07-12_18-03-05", "timestamp": 1657666985, "time_total_s": 68.00589346885681, "pid": 205749, "hostname": "desktop", "node_ip": "127.0.1.1", "config": {"n_layers": 2, "optimizer__lr": 3.056740793738313e-05, "n_head": 8, "n_hid": 64, "dropout": 0.048264643591270306, "numerical_passthrough": true}, "time_since_restore": 68.00589346885681, "timesteps_since_restore": 0, "iterations_since_restore": 5}
{"train_loss": 2.2999711325630523, "valid_loss": 2.2884318429145596, "balanced_accuracy": 0.09090909090909091, "accuracy": 0.32955234744631806, "time_this_iter_s": 12.311678171157837, "done": false, "timesteps_total": null, "episodes_total": null, "training_iteration": 6, "trial_id": "a0875632", "experiment_id": "ba764abc1df047249af424415e270160", "date": "2022-07-12_18-03-18", "timestamp": 1657666998, "time_total_s": 80.31757164001465, "pid": 205749, "hostname": "desktop", "node_ip": "127.0.1.1", "config": {"n_layers": 2, "optimizer__lr": 3.056740793738313e-05, "n_head": 8, "n_hid": 64, "dropout": 0.048264643591270306, "numerical_passthrough": true}, "time_since_restore": 80.31757164001465, "timesteps_since_restore": 0, "iterations_since_restore": 6}
{"train_loss": 2.280023837890727, "valid_loss": 2.2684172189858995, "balanced_accuracy": 0.09090909090909091, "accuracy": 0.32955234744631806, "time_this_iter_s": 11.823114156723022, "done": false, "timesteps_total": null, "episodes_total": null, "training_iteration": 7, "trial_id": "a0875632", "experiment_id": "ba764abc1df047249af424415e270160", "date": "2022-07-12_18-03-29", "timestamp": 1657667009, "time_total_s": 92.14068579673767, "pid": 205749, "hostname": "desktop", "node_ip": "127.0.1.1", "config": {"n_layers": 2, "optimizer__lr": 3.056740793738313e-05, "n_head": 8, "n_hid": 64, "dropout": 0.048264643591270306, "numerical_passthrough": true}, "time_since_restore": 92.14068579673767, "timesteps_since_restore": 0, "iterations_since_restore": 7}
{"train_loss": 2.2603357978690295, "valid_loss": 2.2486338343823347, "balanced_accuracy": 0.09090909090909091, "accuracy": 0.32955234744631806, "time_this_iter_s": 11.69348955154419, "done": false, "timesteps_total": null, "episodes_total": null, "training_iteration": 8, "trial_id": "a0875632", "experiment_id": "ba764abc1df047249af424415e270160", "date": "2022-07-12_18-03-41", "timestamp": 1657667021, "time_total_s": 103.83417534828186, "pid": 205749, "hostname": "desktop", "node_ip": "127.0.1.1", "config": {"n_layers": 2, "optimizer__lr": 3.056740793738313e-05, "n_head": 8, "n_hid": 64, "dropout": 0.048264643591270306, "numerical_passthrough": true}, "time_since_restore": 103.83417534828186, "timesteps_since_restore": 0, "iterations_since_restore": 8}
{"train_loss": 2.2407847164933377, "valid_loss": 2.2290645889701968, "balanced_accuracy": 0.09090909090909091, "accuracy": 0.32955234744631806, "time_this_iter_s": 10.466406345367432, "done": false, "timesteps_total": null, "episodes_total": null, "training_iteration": 9, "trial_id": "a0875632", "experiment_id": "ba764abc1df047249af424415e270160", "date": "2022-07-12_18-03-52", "timestamp": 1657667032, "time_total_s": 114.30058169364929, "pid": 205749, "hostname": "desktop", "node_ip": "127.0.1.1", "config": {"n_layers": 2, "optimizer__lr": 3.056740793738313e-05, "n_head": 8, "n_hid": 64, "dropout": 0.048264643591270306, "numerical_passthrough": true}, "time_since_restore": 114.30058169364929, "timesteps_since_restore": 0, "iterations_since_restore": 9}
{"train_loss": 2.221510657635936, "valid_loss": 2.2097097586243386, "balanced_accuracy": 0.09090909090909091, "accuracy": 0.32955234744631806, "time_this_iter_s": 13.198199033737183, "done": false, "timesteps_total": null, "episodes_total": null, "training_iteration": 10, "trial_id": "a0875632", "experiment_id": "ba764abc1df047249af424415e270160", "date": "2022-07-12_18-04-05", "timestamp": 1657667045, "time_total_s": 127.49878072738647, "pid": 205749, "hostname": "desktop", "node_ip": "127.0.1.1", "config": {"n_layers": 2, "optimizer__lr": 3.056740793738313e-05, "n_head": 8, "n_hid": 64, "dropout": 0.048264643591270306, "numerical_passthrough": true}, "time_since_restore": 127.49878072738647, "timesteps_since_restore": 0, "iterations_since_restore": 10}
{"train_loss": 2.2023696396140586, "valid_loss": 2.190586765746996, "balanced_accuracy": 0.09090909090909091, "accuracy": 0.32955234744631806, "time_this_iter_s": 14.095326900482178, "done": false, "timesteps_total": null, "episodes_total": null, "training_iteration": 11, "trial_id": "a0875632", "experiment_id": "ba764abc1df047249af424415e270160", "date": "2022-07-12_18-04-19", "timestamp": 1657667059, "time_total_s": 141.59410762786865, "pid": 205749, "hostname": "desktop", "node_ip": "127.0.1.1", "config": {"n_layers": 2, "optimizer__lr": 3.056740793738313e-05, "n_head": 8, "n_hid": 64, "dropout": 0.048264643591270306, "numerical_passthrough": true}, "time_since_restore": 141.59410762786865, "timesteps_since_restore": 0, "iterations_since_restore": 11}
{"train_loss": 2.183486031456276, "valid_loss": 2.1717222649741923, "balanced_accuracy": 0.09090909090909091, "accuracy": 0.32955234744631806, "time_this_iter_s": 12.604022741317749, "done": false, "timesteps_total": null, "episodes_total": null, "training_iteration": 12, "trial_id": "a0875632", "experiment_id": "ba764abc1df047249af424415e270160", "date": "2022-07-12_18-04-32", "timestamp": 1657667072, "time_total_s": 154.1981303691864, "pid": 205749, "hostname": "desktop", "node_ip": "127.0.1.1", "config": {"n_layers": 2, "optimizer__lr": 3.056740793738313e-05, "n_head": 8, "n_hid": 64, "dropout": 0.048264643591270306, "numerical_passthrough": true}, "time_since_restore": 154.1981303691864, "timesteps_since_restore": 0, "iterations_since_restore": 12}
{"train_loss": 2.1648524559832714, "valid_loss": 2.1531584159590067, "balanced_accuracy": 0.09090909090909091, "accuracy": 0.32955234744631806, "time_this_iter_s": 11.622695207595825, "done": false, "timesteps_total": null, "episodes_total": null, "training_iteration": 13, "trial_id": "a0875632", "experiment_id": "ba764abc1df047249af424415e270160", "date": "2022-07-12_18-04-43", "timestamp": 1657667083, "time_total_s": 165.82082557678223, "pid": 205749, "hostname": "desktop", "node_ip": "127.0.1.1", "config": {"n_layers": 2, "optimizer__lr": 3.056740793738313e-05, "n_head": 8, "n_hid": 64, "dropout": 0.048264643591270306, "numerical_passthrough": true}, "time_since_restore": 165.82082557678223, "timesteps_since_restore": 0, "iterations_since_restore": 13}
{"train_loss": 2.1464581034592194, "valid_loss": 2.1349492929780944, "balanced_accuracy": 0.09090909090909091, "accuracy": 0.32955234744631806, "time_this_iter_s": 12.17020845413208, "done": false, "timesteps_total": null, "episodes_total": null, "training_iteration": 14, "trial_id": "a0875632", "experiment_id": "ba764abc1df047249af424415e270160", "date": "2022-07-12_18-04-55", "timestamp": 1657667095, "time_total_s": 177.9910340309143, "pid": 205749, "hostname": "desktop", "node_ip": "127.0.1.1", "config": {"n_layers": 2, "optimizer__lr": 3.056740793738313e-05, "n_head": 8, "n_hid": 64, "dropout": 0.048264643591270306, "numerical_passthrough": true}, "time_since_restore": 177.9910340309143, "timesteps_since_restore": 0, "iterations_since_restore": 14}
{"train_loss": 2.128445448956992, "valid_loss": 2.117152095954568, "balanced_accuracy": 0.09090909090909091, "accuracy": 0.32955234744631806, "time_this_iter_s": 12.583693027496338, "done": false, "timesteps_total": null, "episodes_total": null, "training_iteration": 15, "trial_id": "a0875632", "experiment_id": "ba764abc1df047249af424415e270160", "date": "2022-07-12_18-05-08", "timestamp": 1657667108, "time_total_s": 190.57472705841064, "pid": 205749, "hostname": "desktop", "node_ip": "127.0.1.1", "config": {"n_layers": 2, "optimizer__lr": 3.056740793738313e-05, "n_head": 8, "n_hid": 64, "dropout": 0.048264643591270306, "numerical_passthrough": true}, "time_since_restore": 190.57472705841064, "timesteps_since_restore": 0, "iterations_since_restore": 15}
{"train_loss": 2.1108528501588597, "valid_loss": 2.0998370630076164, "balanced_accuracy": 0.09090909090909091, "accuracy": 0.32955234744631806, "time_this_iter_s": 13.510842323303223, "done": false, "timesteps_total": null, "episodes_total": null, "training_iteration": 16, "trial_id": "a0875632", "experiment_id": "ba764abc1df047249af424415e270160", "date": "2022-07-12_18-05-21", "timestamp": 1657667121, "time_total_s": 204.08556938171387, "pid": 205749, "hostname": "desktop", "node_ip": "127.0.1.1", "config": {"n_layers": 2, "optimizer__lr": 3.056740793738313e-05, "n_head": 8, "n_hid": 64, "dropout": 0.048264643591270306, "numerical_passthrough": true}, "time_since_restore": 204.08556938171387, "timesteps_since_restore": 0, "iterations_since_restore": 16}
{"train_loss": 2.093679559819403, "valid_loss": 2.0830709725405048, "balanced_accuracy": 0.09090909090909091, "accuracy": 0.32955234744631806, "time_this_iter_s": 14.055256366729736, "done": false, "timesteps_total": null, "episodes_total": null, "training_iteration": 17, "trial_id": "a0875632", "experiment_id": "ba764abc1df047249af424415e270160", "date": "2022-07-12_18-05-35", "timestamp": 1657667135, "time_total_s": 218.1408257484436, "pid": 205749, "hostname": "desktop", "node_ip": "127.0.1.1", "config": {"n_layers": 2, "optimizer__lr": 3.056740793738313e-05, "n_head": 8, "n_hid": 64, "dropout": 0.048264643591270306, "numerical_passthrough": true}, "time_since_restore": 218.1408257484436, "timesteps_since_restore": 0, "iterations_since_restore": 17}
{"train_loss": 2.0771047238020532, "valid_loss": 2.0669246681046314, "balanced_accuracy": 0.09090909090909091, "accuracy": 0.32955234744631806, "time_this_iter_s": 13.027884244918823, "done": false, "timesteps_total": null, "episodes_total": null, "training_iteration": 18, "trial_id": "a0875632", "experiment_id": "ba764abc1df047249af424415e270160", "date": "2022-07-12_18-05-48", "timestamp": 1657667148, "time_total_s": 231.16870999336243, "pid": 205749, "hostname": "desktop", "node_ip": "127.0.1.1", "config": {"n_layers": 2, "optimizer__lr": 3.056740793738313e-05, "n_head": 8, "n_hid": 64, "dropout": 0.048264643591270306, "numerical_passthrough": true}, "time_since_restore": 231.16870999336243, "timesteps_since_restore": 0, "iterations_since_restore": 18}
{"train_loss": 2.0611309745741835, "valid_loss": 2.051459300435603, "balanced_accuracy": 0.09090909090909091, "accuracy": 0.32955234744631806, "time_this_iter_s": 14.36408805847168, "done": false, "timesteps_total": null, "episodes_total": null, "training_iteration": 19, "trial_id": "a0875632", "experiment_id": "ba764abc1df047249af424415e270160", "date": "2022-07-12_18-06-03", "timestamp": 1657667163, "time_total_s": 245.5327980518341, "pid": 205749, "hostname": "desktop", "node_ip": "127.0.1.1", "config": {"n_layers": 2, "optimizer__lr": 3.056740793738313e-05, "n_head": 8, "n_hid": 64, "dropout": 0.048264643591270306, "numerical_passthrough": true}, "time_since_restore": 245.5327980518341, "timesteps_since_restore": 0, "iterations_since_restore": 19}
{"train_loss": 2.04588987354976, "valid_loss": 2.0367347344052917, "balanced_accuracy": 0.09090909090909091, "accuracy": 0.32955234744631806, "time_this_iter_s": 10.873698949813843, "done": false, "timesteps_total": null, "episodes_total": null, "training_iteration": 20, "trial_id": "a0875632", "experiment_id": "ba764abc1df047249af424415e270160", "date": "2022-07-12_18-06-14", "timestamp": 1657667174, "time_total_s": 256.40649700164795, "pid": 205749, "hostname": "desktop", "node_ip": "127.0.1.1", "config": {"n_layers": 2, "optimizer__lr": 3.056740793738313e-05, "n_head": 8, "n_hid": 64, "dropout": 0.048264643591270306, "numerical_passthrough": true}, "time_since_restore": 256.40649700164795, "timesteps_since_restore": 0, "iterations_since_restore": 20}
{"train_loss": 2.0313212671399072, "valid_loss": 2.0227907028907453, "balanced_accuracy": 0.09090909090909091, "accuracy": 0.32955234744631806, "time_this_iter_s": 14.115187168121338, "done": false, "timesteps_total": null, "episodes_total": null, "training_iteration": 21, "trial_id": "a0875632", "experiment_id": "ba764abc1df047249af424415e270160", "date": "2022-07-12_18-06-28", "timestamp": 1657667188, "time_total_s": 270.5216841697693, "pid": 205749, "hostname": "desktop", "node_ip": "127.0.1.1", "config": {"n_layers": 2, "optimizer__lr": 3.056740793738313e-05, "n_head": 8, "n_hid": 64, "dropout": 0.048264643591270306, "numerical_passthrough": true}, "time_since_restore": 270.5216841697693, "timesteps_since_restore": 0, "iterations_since_restore": 21}
{"train_loss": 2.017504459733048, "valid_loss": 2.009658106507483, "balanced_accuracy": 0.09090909090909091, "accuracy": 0.32955234744631806, "time_this_iter_s": 14.132256507873535, "done": false, "timesteps_total": null, "episodes_total": null, "training_iteration": 22, "trial_id": "a0875632", "experiment_id": "ba764abc1df047249af424415e270160", "date": "2022-07-12_18-06-42", "timestamp": 1657667202, "time_total_s": 284.6539406776428, "pid": 205749, "hostname": "desktop", "node_ip": "127.0.1.1", "config": {"n_layers": 2, "optimizer__lr": 3.056740793738313e-05, "n_head": 8, "n_hid": 64, "dropout": 0.048264643591270306, "numerical_passthrough": true}, "time_since_restore": 284.6539406776428, "timesteps_since_restore": 0, "iterations_since_restore": 22}
{"train_loss": 2.0043948383335928, "valid_loss": 1.9973542965631323, "balanced_accuracy": 0.09090909090909091, "accuracy": 0.32955234744631806, "time_this_iter_s": 11.511810064315796, "done": false, "timesteps_total": null, "episodes_total": null, "training_iteration": 23, "trial_id": "a0875632", "experiment_id": "ba764abc1df047249af424415e270160", "date": "2022-07-12_18-06-53", "timestamp": 1657667213, "time_total_s": 296.1657507419586, "pid": 205749, "hostname": "desktop", "node_ip": "127.0.1.1", "config": {"n_layers": 2, "optimizer__lr": 3.056740793738313e-05, "n_head": 8, "n_hid": 64, "dropout": 0.048264643591270306, "numerical_passthrough": true}, "time_since_restore": 296.1657507419586, "timesteps_since_restore": 0, "iterations_since_restore": 23}
{"train_loss": 1.9922185047555285, "valid_loss": 1.9858850826702839, "balanced_accuracy": 0.09090909090909091, "accuracy": 0.32955234744631806, "time_this_iter_s": 12.966536045074463, "done": false, "timesteps_total": null, "episodes_total": null, "training_iteration": 24, "trial_id": "a0875632", "experiment_id": "ba764abc1df047249af424415e270160", "date": "2022-07-12_18-07-06", "timestamp": 1657667226, "time_total_s": 309.1322867870331, "pid": 205749, "hostname": "desktop", "node_ip": "127.0.1.1", "config": {"n_layers": 2, "optimizer__lr": 3.056740793738313e-05, "n_head": 8, "n_hid": 64, "dropout": 0.048264643591270306, "numerical_passthrough": true}, "time_since_restore": 309.1322867870331, "timesteps_since_restore": 0, "iterations_since_restore": 24}
{"train_loss": 1.9808036940169829, "valid_loss": 1.9752363615008244, "balanced_accuracy": 0.09090909090909091, "accuracy": 0.32955234744631806, "time_this_iter_s": 11.89177393913269, "done": false, "timesteps_total": null, "episodes_total": null, "training_iteration": 25, "trial_id": "a0875632", "experiment_id": "ba764abc1df047249af424415e270160", "date": "2022-07-12_18-07-18", "timestamp": 1657667238, "time_total_s": 321.02406072616577, "pid": 205749, "hostname": "desktop", "node_ip": "127.0.1.1", "config": {"n_layers": 2, "optimizer__lr": 3.056740793738313e-05, "n_head": 8, "n_hid": 64, "dropout": 0.048264643591270306, "numerical_passthrough": true}, "time_since_restore": 321.02406072616577, "timesteps_since_restore": 0, "iterations_since_restore": 25}
{"train_loss": 1.9702082110538828, "valid_loss": 1.9653848181588838, "balanced_accuracy": 0.09090909090909091, "accuracy": 0.32955234744631806, "time_this_iter_s": 13.817405462265015, "done": false, "timesteps_total": null, "episodes_total": null, "training_iteration": 26, "trial_id": "a0875632", "experiment_id": "ba764abc1df047249af424415e270160", "date": "2022-07-12_18-07-32", "timestamp": 1657667252, "time_total_s": 334.8414661884308, "pid": 205749, "hostname": "desktop", "node_ip": "127.0.1.1", "config": {"n_layers": 2, "optimizer__lr": 3.056740793738313e-05, "n_head": 8, "n_hid": 64, "dropout": 0.048264643591270306, "numerical_passthrough": true}, "time_since_restore": 334.8414661884308, "timesteps_since_restore": 0, "iterations_since_restore": 26}
{"train_loss": 1.9602927994875599, "valid_loss": 1.9562920686560292, "balanced_accuracy": 0.09090909090909091, "accuracy": 0.32955234744631806, "time_this_iter_s": 12.987859010696411, "done": false, "timesteps_total": null, "episodes_total": null, "training_iteration": 27, "trial_id": "a0875632", "experiment_id": "ba764abc1df047249af424415e270160", "date": "2022-07-12_18-07-45", "timestamp": 1657667265, "time_total_s": 347.8293251991272, "pid": 205749, "hostname": "desktop", "node_ip": "127.0.1.1", "config": {"n_layers": 2, "optimizer__lr": 3.056740793738313e-05, "n_head": 8, "n_hid": 64, "dropout": 0.048264643591270306, "numerical_passthrough": true}, "time_since_restore": 347.8293251991272, "timesteps_since_restore": 0, "iterations_since_restore": 27}
{"train_loss": 1.9511206788257764, "valid_loss": 1.9479192578935745, "balanced_accuracy": 0.09090909090909091, "accuracy": 0.32955234744631806, "time_this_iter_s": 14.212278842926025, "done": false, "timesteps_total": null, "episodes_total": null, "training_iteration": 28, "trial_id": "a0875632", "experiment_id": "ba764abc1df047249af424415e270160", "date": "2022-07-12_18-07-59", "timestamp": 1657667279, "time_total_s": 362.0416040420532, "pid": 205749, "hostname": "desktop", "node_ip": "127.0.1.1", "config": {"n_layers": 2, "optimizer__lr": 3.056740793738313e-05, "n_head": 8, "n_hid": 64, "dropout": 0.048264643591270306, "numerical_passthrough": true}, "time_since_restore": 362.0416040420532, "timesteps_since_restore": 0, "iterations_since_restore": 28}
{"train_loss": 1.9427383004874261, "valid_loss": 1.9402175264915014, "balanced_accuracy": 0.09090909090909091, "accuracy": 0.32955234744631806, "time_this_iter_s": 13.25108289718628, "done": false, "timesteps_total": null, "episodes_total": null, "training_iteration": 29, "trial_id": "a0875632", "experiment_id": "ba764abc1df047249af424415e270160", "date": "2022-07-12_18-08-13", "timestamp": 1657667293, "time_total_s": 375.2926869392395, "pid": 205749, "hostname": "desktop", "node_ip": "127.0.1.1", "config": {"n_layers": 2, "optimizer__lr": 3.056740793738313e-05, "n_head": 8, "n_hid": 64, "dropout": 0.048264643591270306, "numerical_passthrough": true}, "time_since_restore": 375.2926869392395, "timesteps_since_restore": 0, "iterations_since_restore": 29}
{"train_loss": 1.9349279313589, "valid_loss": 1.9331333847947163, "balanced_accuracy": 0.09090909090909091, "accuracy": 0.32955234744631806, "time_this_iter_s": 11.830668449401855, "done": false, "timesteps_total": null, "episodes_total": null, "training_iteration": 30, "trial_id": "a0875632", "experiment_id": "ba764abc1df047249af424415e270160", "date": "2022-07-12_18-08-24", "timestamp": 1657667304, "time_total_s": 387.12335538864136, "pid": 205749, "hostname": "desktop", "node_ip": "127.0.1.1", "config": {"n_layers": 2, "optimizer__lr": 3.056740793738313e-05, "n_head": 8, "n_hid": 64, "dropout": 0.048264643591270306, "numerical_passthrough": true}, "time_since_restore": 387.12335538864136, "timesteps_since_restore": 0, "iterations_since_restore": 30}
{"train_loss": 1.9276691926967515, "valid_loss": 1.9266167829211123, "balanced_accuracy": 0.09090909090909091, "accuracy": 0.32955234744631806, "time_this_iter_s": 13.359922647476196, "done": false, "timesteps_total": null, "episodes_total": null, "training_iteration": 31, "trial_id": "a0875632", "experiment_id": "ba764abc1df047249af424415e270160", "date": "2022-07-12_18-08-38", "timestamp": 1657667318, "time_total_s": 400.48327803611755, "pid": 205749, "hostname": "desktop", "node_ip": "127.0.1.1", "config": {"n_layers": 2, "optimizer__lr": 3.056740793738313e-05, "n_head": 8, "n_hid": 64, "dropout": 0.048264643591270306, "numerical_passthrough": true}, "time_since_restore": 400.48327803611755, "timesteps_since_restore": 0, "iterations_since_restore": 31}
{"train_loss": 1.9210135554075676, "valid_loss": 1.920620045701841, "balanced_accuracy": 0.09090909090909091, "accuracy": 0.32955234744631806, "time_this_iter_s": 13.438317060470581, "done": false, "timesteps_total": null, "episodes_total": null, "training_iteration": 32, "trial_id": "a0875632", "experiment_id": "ba764abc1df047249af424415e270160", "date": "2022-07-12_18-08-51", "timestamp": 1657667331, "time_total_s": 413.92159509658813, "pid": 205749, "hostname": "desktop", "node_ip": "127.0.1.1", "config": {"n_layers": 2, "optimizer__lr": 3.056740793738313e-05, "n_head": 8, "n_hid": 64, "dropout": 0.048264643591270306, "numerical_passthrough": true}, "time_since_restore": 413.92159509658813, "timesteps_since_restore": 0, "iterations_since_restore": 32}
{"train_loss": 1.9148017296177315, "valid_loss": 1.9150918389963292, "balanced_accuracy": 0.09090909090909091, "accuracy": 0.32955234744631806, "time_this_iter_s": 12.376301050186157, "done": false, "timesteps_total": null, "episodes_total": null, "training_iteration": 33, "trial_id": "a0875632", "experiment_id": "ba764abc1df047249af424415e270160", "date": "2022-07-12_18-09-04", "timestamp": 1657667344, "time_total_s": 426.2978961467743, "pid": 205749, "hostname": "desktop", "node_ip": "127.0.1.1", "config": {"n_layers": 2, "optimizer__lr": 3.056740793738313e-05, "n_head": 8, "n_hid": 64, "dropout": 0.048264643591270306, "numerical_passthrough": true}, "time_since_restore": 426.2978961467743, "timesteps_since_restore": 0, "iterations_since_restore": 33}
{"train_loss": 1.9090808309948186, "valid_loss": 1.909987934205799, "balanced_accuracy": 0.09090909090909091, "accuracy": 0.32955234744631806, "time_this_iter_s": 11.752676248550415, "done": false, "timesteps_total": null, "episodes_total": null, "training_iteration": 34, "trial_id": "a0875632", "experiment_id": "ba764abc1df047249af424415e270160", "date": "2022-07-12_18-09-15", "timestamp": 1657667355, "time_total_s": 438.0505723953247, "pid": 205749, "hostname": "desktop", "node_ip": "127.0.1.1", "config": {"n_layers": 2, "optimizer__lr": 3.056740793738313e-05, "n_head": 8, "n_hid": 64, "dropout": 0.048264643591270306, "numerical_passthrough": true}, "time_since_restore": 438.0505723953247, "timesteps_since_restore": 0, "iterations_since_restore": 34}
{"train_loss": 1.9038345981653666, "valid_loss": 1.905267585875643, "balanced_accuracy": 0.09090909090909091, "accuracy": 0.32955234744631806, "time_this_iter_s": 12.110056400299072, "done": false, "timesteps_total": null, "episodes_total": null, "training_iteration": 35, "trial_id": "a0875632", "experiment_id": "ba764abc1df047249af424415e270160", "date": "2022-07-12_18-09-27", "timestamp": 1657667367, "time_total_s": 450.1606287956238, "pid": 205749, "hostname": "desktop", "node_ip": "127.0.1.1", "config": {"n_layers": 2, "optimizer__lr": 3.056740793738313e-05, "n_head": 8, "n_hid": 64, "dropout": 0.048264643591270306, "numerical_passthrough": true}, "time_since_restore": 450.1606287956238, "timesteps_since_restore": 0, "iterations_since_restore": 35}
{"train_loss": 1.8989109508363307, "valid_loss": 1.9008922150857266, "balanced_accuracy": 0.09090909090909091, "accuracy": 0.32955234744631806, "time_this_iter_s": 12.683817863464355, "done": false, "timesteps_total": null, "episodes_total": null, "training_iteration": 36, "trial_id": "a0875632", "experiment_id": "ba764abc1df047249af424415e270160", "date": "2022-07-12_18-09-40", "timestamp": 1657667380, "time_total_s": 462.84444665908813, "pid": 205749, "hostname": "desktop", "node_ip": "127.0.1.1", "config": {"n_layers": 2, "optimizer__lr": 3.056740793738313e-05, "n_head": 8, "n_hid": 64, "dropout": 0.048264643591270306, "numerical_passthrough": true}, "time_since_restore": 462.84444665908813, "timesteps_since_restore": 0, "iterations_since_restore": 36}
{"train_loss": 1.894397330648558, "valid_loss": 1.8968284897733108, "balanced_accuracy": 0.09090909090909091, "accuracy": 0.32955234744631806, "time_this_iter_s": 14.410547494888306, "done": false, "timesteps_total": null, "episodes_total": null, "training_iteration": 37, "trial_id": "a0875632", "experiment_id": "ba764abc1df047249af424415e270160", "date": "2022-07-12_18-09-55", "timestamp": 1657667395, "time_total_s": 477.25499415397644, "pid": 205749, "hostname": "desktop", "node_ip": "127.0.1.1", "config": {"n_layers": 2, "optimizer__lr": 3.056740793738313e-05, "n_head": 8, "n_hid": 64, "dropout": 0.048264643591270306, "numerical_passthrough": true}, "time_since_restore": 477.25499415397644, "timesteps_since_restore": 0, "iterations_since_restore": 37}
{"train_loss": 1.8901078834502454, "valid_loss": 1.8930456643831697, "balanced_accuracy": 0.09090909090909091, "accuracy": 0.32955234744631806, "time_this_iter_s": 13.733507633209229, "done": false, "timesteps_total": null, "episodes_total": null, "training_iteration": 38, "trial_id": "a0875632", "experiment_id": "ba764abc1df047249af424415e270160", "date": "2022-07-12_18-10-08", "timestamp": 1657667408, "time_total_s": 490.98850178718567, "pid": 205749, "hostname": "desktop", "node_ip": "127.0.1.1", "config": {"n_layers": 2, "optimizer__lr": 3.056740793738313e-05, "n_head": 8, "n_hid": 64, "dropout": 0.048264643591270306, "numerical_passthrough": true}, "time_since_restore": 490.98850178718567, "timesteps_since_restore": 0, "iterations_since_restore": 38}
{"train_loss": 1.886114329298506, "valid_loss": 1.889519295688973, "balanced_accuracy": 0.09090909090909091, "accuracy": 0.32955234744631806, "time_this_iter_s": 14.137836456298828, "done": false, "timesteps_total": null, "episodes_total": null, "training_iteration": 39, "trial_id": "a0875632", "experiment_id": "ba764abc1df047249af424415e270160", "date": "2022-07-12_18-10-22", "timestamp": 1657667422, "time_total_s": 505.1263382434845, "pid": 205749, "hostname": "desktop", "node_ip": "127.0.1.1", "config": {"n_layers": 2, "optimizer__lr": 3.056740793738313e-05, "n_head": 8, "n_hid": 64, "dropout": 0.048264643591270306, "numerical_passthrough": true}, "time_since_restore": 505.1263382434845, "timesteps_since_restore": 0, "iterations_since_restore": 39}
{"train_loss": 1.8823206381616728, "valid_loss": 1.886223432307074, "balanced_accuracy": 0.09090909090909091, "accuracy": 0.32955234744631806, "time_this_iter_s": 11.966960668563843, "done": false, "timesteps_total": null, "episodes_total": null, "training_iteration": 40, "trial_id": "a0875632", "experiment_id": "ba764abc1df047249af424415e270160", "date": "2022-07-12_18-10-34", "timestamp": 1657667434, "time_total_s": 517.0932989120483, "pid": 205749, "hostname": "desktop", "node_ip": "127.0.1.1", "config": {"n_layers": 2, "optimizer__lr": 3.056740793738313e-05, "n_head": 8, "n_hid": 64, "dropout": 0.048264643591270306, "numerical_passthrough": true}, "time_since_restore": 517.0932989120483, "timesteps_since_restore": 0, "iterations_since_restore": 40}
{"train_loss": 1.8789331219113308, "valid_loss": 1.883139025321881, "balanced_accuracy": 0.09090909090909091, "accuracy": 0.32955234744631806, "time_this_iter_s": 13.846217393875122, "done": false, "timesteps_total": null, "episodes_total": null, "training_iteration": 41, "trial_id": "a0875632", "experiment_id": "ba764abc1df047249af424415e270160", "date": "2022-07-12_18-10-48", "timestamp": 1657667448, "time_total_s": 530.9395163059235, "pid": 205749, "hostname": "desktop", "node_ip": "127.0.1.1", "config": {"n_layers": 2, "optimizer__lr": 3.056740793738313e-05, "n_head": 8, "n_hid": 64, "dropout": 0.048264643591270306, "numerical_passthrough": true}, "time_since_restore": 530.9395163059235, "timesteps_since_restore": 0, "iterations_since_restore": 41}
{"train_loss": 1.8755875750680173, "valid_loss": 1.8802450780771347, "balanced_accuracy": 0.09090909090909091, "accuracy": 0.32955234744631806, "time_this_iter_s": 13.111777305603027, "done": false, "timesteps_total": null, "episodes_total": null, "training_iteration": 42, "trial_id": "a0875632", "experiment_id": "ba764abc1df047249af424415e270160", "date": "2022-07-12_18-11-01", "timestamp": 1657667461, "time_total_s": 544.0512936115265, "pid": 205749, "hostname": "desktop", "node_ip": "127.0.1.1", "config": {"n_layers": 2, "optimizer__lr": 3.056740793738313e-05, "n_head": 8, "n_hid": 64, "dropout": 0.048264643591270306, "numerical_passthrough": true}, "time_since_restore": 544.0512936115265, "timesteps_since_restore": 0, "iterations_since_restore": 42}
{"train_loss": 1.8724023858913443, "valid_loss": 1.8775250739905494, "balanced_accuracy": 0.09090909090909091, "accuracy": 0.32955234744631806, "time_this_iter_s": 14.038288354873657, "done": false, "timesteps_total": null, "episodes_total": null, "training_iteration": 43, "trial_id": "a0875632", "experiment_id": "ba764abc1df047249af424415e270160", "date": "2022-07-12_18-11-15", "timestamp": 1657667475, "time_total_s": 558.0895819664001, "pid": 205749, "hostname": "desktop", "node_ip": "127.0.1.1", "config": {"n_layers": 2, "optimizer__lr": 3.056740793738313e-05, "n_head": 8, "n_hid": 64, "dropout": 0.048264643591270306, "numerical_passthrough": true}, "time_since_restore": 558.0895819664001, "timesteps_since_restore": 0, "iterations_since_restore": 43}
{"train_loss": 1.8694818778681868, "valid_loss": 1.8749650371431885, "balanced_accuracy": 0.09090909090909091, "accuracy": 0.32955234744631806, "time_this_iter_s": 13.466507911682129, "done": false, "timesteps_total": null, "episodes_total": null, "training_iteration": 44, "trial_id": "a0875632", "experiment_id": "ba764abc1df047249af424415e270160", "date": "2022-07-12_18-11-29", "timestamp": 1657667489, "time_total_s": 571.5560898780823, "pid": 205749, "hostname": "desktop", "node_ip": "127.0.1.1", "config": {"n_layers": 2, "optimizer__lr": 3.056740793738313e-05, "n_head": 8, "n_hid": 64, "dropout": 0.048264643591270306, "numerical_passthrough": true}, "time_since_restore": 571.5560898780823, "timesteps_since_restore": 0, "iterations_since_restore": 44}
{"train_loss": 1.8668581860224251, "valid_loss": 1.872552267211915, "balanced_accuracy": 0.09090909090909091, "accuracy": 0.32955234744631806, "time_this_iter_s": 14.309447050094604, "done": false, "timesteps_total": null, "episodes_total": null, "training_iteration": 45, "trial_id": "a0875632", "experiment_id": "ba764abc1df047249af424415e270160", "date": "2022-07-12_18-11-43", "timestamp": 1657667503, "time_total_s": 585.8655369281769, "pid": 205749, "hostname": "desktop", "node_ip": "127.0.1.1", "config": {"n_layers": 2, "optimizer__lr": 3.056740793738313e-05, "n_head": 8, "n_hid": 64, "dropout": 0.048264643591270306, "numerical_passthrough": true}, "time_since_restore": 585.8655369281769, "timesteps_since_restore": 0, "iterations_since_restore": 45}
{"train_loss": 1.8642574681192148, "valid_loss": 1.8702727861518957, "balanced_accuracy": 0.09090909090909091, "accuracy": 0.32955234744631806, "time_this_iter_s": 13.089242458343506, "done": false, "timesteps_total": null, "episodes_total": null, "training_iteration": 46, "trial_id": "a0875632", "experiment_id": "ba764abc1df047249af424415e270160", "date": "2022-07-12_18-11-56", "timestamp": 1657667516, "time_total_s": 598.9547793865204, "pid": 205749, "hostname": "desktop", "node_ip": "127.0.1.1", "config": {"n_layers": 2, "optimizer__lr": 3.056740793738313e-05, "n_head": 8, "n_hid": 64, "dropout": 0.048264643591270306, "numerical_passthrough": true}, "time_since_restore": 598.9547793865204, "timesteps_since_restore": 0, "iterations_since_restore": 46}
{"train_loss": 1.8618481198257286, "valid_loss": 1.8681168773720078, "balanced_accuracy": 0.09090909090909091, "accuracy": 0.32955234744631806, "time_this_iter_s": 12.641857862472534, "done": false, "timesteps_total": null, "episodes_total": null, "training_iteration": 47, "trial_id": "a0875632", "experiment_id": "ba764abc1df047249af424415e270160", "date": "2022-07-12_18-12-09", "timestamp": 1657667529, "time_total_s": 611.5966372489929, "pid": 205749, "hostname": "desktop", "node_ip": "127.0.1.1", "config": {"n_layers": 2, "optimizer__lr": 3.056740793738313e-05, "n_head": 8, "n_hid": 64, "dropout": 0.048264643591270306, "numerical_passthrough": true}, "time_since_restore": 611.5966372489929, "timesteps_since_restore": 0, "iterations_since_restore": 47}
{"train_loss": 1.8594863247295816, "valid_loss": 1.8660739634954768, "balanced_accuracy": 0.09090909090909091, "accuracy": 0.32955234744631806, "time_this_iter_s": 12.836066961288452, "done": false, "timesteps_total": null, "episodes_total": null, "training_iteration": 48, "trial_id": "a0875632", "experiment_id": "ba764abc1df047249af424415e270160", "date": "2022-07-12_18-12-22", "timestamp": 1657667542, "time_total_s": 624.4327042102814, "pid": 205749, "hostname": "desktop", "node_ip": "127.0.1.1", "config": {"n_layers": 2, "optimizer__lr": 3.056740793738313e-05, "n_head": 8, "n_hid": 64, "dropout": 0.048264643591270306, "numerical_passthrough": true}, "time_since_restore": 624.4327042102814, "timesteps_since_restore": 0, "iterations_since_restore": 48}
{"train_loss": 1.8572279619502454, "valid_loss": 1.8641360990922746, "balanced_accuracy": 0.09090909090909091, "accuracy": 0.32955234744631806, "time_this_iter_s": 13.61334776878357, "done": false, "timesteps_total": null, "episodes_total": null, "training_iteration": 49, "trial_id": "a0875632", "experiment_id": "ba764abc1df047249af424415e270160", "date": "2022-07-12_18-12-35", "timestamp": 1657667555, "time_total_s": 638.0460519790649, "pid": 205749, "hostname": "desktop", "node_ip": "127.0.1.1", "config": {"n_layers": 2, "optimizer__lr": 3.056740793738313e-05, "n_head": 8, "n_hid": 64, "dropout": 0.048264643591270306, "numerical_passthrough": true}, "time_since_restore": 638.0460519790649, "timesteps_since_restore": 0, "iterations_since_restore": 49}
{"train_loss": 1.8552456367049102, "valid_loss": 1.862294829674142, "balanced_accuracy": 0.09090909090909091, "accuracy": 0.32955234744631806, "time_this_iter_s": 13.055856466293335, "done": false, "timesteps_total": null, "episodes_total": null, "training_iteration": 50, "trial_id": "a0875632", "experiment_id": "ba764abc1df047249af424415e270160", "date": "2022-07-12_18-12-48", "timestamp": 1657667568, "time_total_s": 651.1019084453583, "pid": 205749, "hostname": "desktop", "node_ip": "127.0.1.1", "config": {"n_layers": 2, "optimizer__lr": 3.056740793738313e-05, "n_head": 8, "n_hid": 64, "dropout": 0.048264643591270306, "numerical_passthrough": true}, "time_since_restore": 651.1019084453583, "timesteps_since_restore": 0, "iterations_since_restore": 50}
{"train_loss": 1.8532036577456352, "valid_loss": 1.8605422758584633, "balanced_accuracy": 0.09090909090909091, "accuracy": 0.32955234744631806, "time_this_iter_s": 11.5270254611969, "done": false, "timesteps_total": null, "episodes_total": null, "training_iteration": 51, "trial_id": "a0875632", "experiment_id": "ba764abc1df047249af424415e270160", "date": "2022-07-12_18-13-00", "timestamp": 1657667580, "time_total_s": 662.6289339065552, "pid": 205749, "hostname": "desktop", "node_ip": "127.0.1.1", "config": {"n_layers": 2, "optimizer__lr": 3.056740793738313e-05, "n_head": 8, "n_hid": 64, "dropout": 0.048264643591270306, "numerical_passthrough": true}, "time_since_restore": 662.6289339065552, "timesteps_since_restore": 0, "iterations_since_restore": 51}
{"train_loss": 1.8512795246386433, "valid_loss": 1.8588721946679054, "balanced_accuracy": 0.09090909090909091, "accuracy": 0.32955234744631806, "time_this_iter_s": 13.855210304260254, "done": false, "timesteps_total": null, "episodes_total": null, "training_iteration": 52, "trial_id": "a0875632", "experiment_id": "ba764abc1df047249af424415e270160", "date": "2022-07-12_18-13-14", "timestamp": 1657667594, "time_total_s": 676.4841442108154, "pid": 205749, "hostname": "desktop", "node_ip": "127.0.1.1", "config": {"n_layers": 2, "optimizer__lr": 3.056740793738313e-05, "n_head": 8, "n_hid": 64, "dropout": 0.048264643591270306, "numerical_passthrough": true}, "time_since_restore": 676.4841442108154, "timesteps_since_restore": 0, "iterations_since_restore": 52}
{"train_loss": 1.8495356547345123, "valid_loss": 1.8572787410438054, "balanced_accuracy": 0.09090909090909091, "accuracy": 0.32955234744631806, "time_this_iter_s": 13.74540090560913, "done": false, "timesteps_total": null, "episodes_total": null, "training_iteration": 53, "trial_id": "a0875632", "experiment_id": "ba764abc1df047249af424415e270160", "date": "2022-07-12_18-13-28", "timestamp": 1657667608, "time_total_s": 690.2295451164246, "pid": 205749, "hostname": "desktop", "node_ip": "127.0.1.1", "config": {"n_layers": 2, "optimizer__lr": 3.056740793738313e-05, "n_head": 8, "n_hid": 64, "dropout": 0.048264643591270306, "numerical_passthrough": true}, "time_since_restore": 690.2295451164246, "timesteps_since_restore": 0, "iterations_since_restore": 53}
{"train_loss": 1.8477625895454715, "valid_loss": 1.8557559543047573, "balanced_accuracy": 0.09090909090909091, "accuracy": 0.32955234744631806, "time_this_iter_s": 13.214290380477905, "done": false, "timesteps_total": null, "episodes_total": null, "training_iteration": 54, "trial_id": "a0875632", "experiment_id": "ba764abc1df047249af424415e270160", "date": "2022-07-12_18-13-41", "timestamp": 1657667621, "time_total_s": 703.4438354969025, "pid": 205749, "hostname": "desktop", "node_ip": "127.0.1.1", "config": {"n_layers": 2, "optimizer__lr": 3.056740793738313e-05, "n_head": 8, "n_hid": 64, "dropout": 0.048264643591270306, "numerical_passthrough": true}, "time_since_restore": 703.4438354969025, "timesteps_since_restore": 0, "iterations_since_restore": 54}
{"train_loss": 1.8460685098892882, "valid_loss": 1.8542988084841452, "balanced_accuracy": 0.09090909090909091, "accuracy": 0.32955234744631806, "time_this_iter_s": 14.205691814422607, "done": false, "timesteps_total": null, "episodes_total": null, "training_iteration": 55, "trial_id": "a0875632", "experiment_id": "ba764abc1df047249af424415e270160", "date": "2022-07-12_18-13-55", "timestamp": 1657667635, "time_total_s": 717.6495273113251, "pid": 205749, "hostname": "desktop", "node_ip": "127.0.1.1", "config": {"n_layers": 2, "optimizer__lr": 3.056740793738313e-05, "n_head": 8, "n_hid": 64, "dropout": 0.048264643591270306, "numerical_passthrough": true}, "time_since_restore": 717.6495273113251, "timesteps_since_restore": 0, "iterations_since_restore": 55}
{"train_loss": 1.8444819639105972, "valid_loss": 1.8529029964287131, "balanced_accuracy": 0.09090909090909091, "accuracy": 0.32955234744631806, "time_this_iter_s": 14.8173668384552, "done": false, "timesteps_total": null, "episodes_total": null, "training_iteration": 56, "trial_id": "a0875632", "experiment_id": "ba764abc1df047249af424415e270160", "date": "2022-07-12_18-14-10", "timestamp": 1657667650, "time_total_s": 732.4668941497803, "pid": 205749, "hostname": "desktop", "node_ip": "127.0.1.1", "config": {"n_layers": 2, "optimizer__lr": 3.056740793738313e-05, "n_head": 8, "n_hid": 64, "dropout": 0.048264643591270306, "numerical_passthrough": true}, "time_since_restore": 732.4668941497803, "timesteps_since_restore": 0, "iterations_since_restore": 56}
{"train_loss": 1.8430303732313087, "valid_loss": 1.8515642893107556, "balanced_accuracy": 0.09090909090909091, "accuracy": 0.32955234744631806, "time_this_iter_s": 11.790254592895508, "done": false, "timesteps_total": null, "episodes_total": null, "training_iteration": 57, "trial_id": "a0875632", "experiment_id": "ba764abc1df047249af424415e270160", "date": "2022-07-12_18-14-22", "timestamp": 1657667662, "time_total_s": 744.2571487426758, "pid": 205749, "hostname": "desktop", "node_ip": "127.0.1.1", "config": {"n_layers": 2, "optimizer__lr": 3.056740793738313e-05, "n_head": 8, "n_hid": 64, "dropout": 0.048264643591270306, "numerical_passthrough": true}, "time_since_restore": 744.2571487426758, "timesteps_since_restore": 0, "iterations_since_restore": 57}
{"train_loss": 1.8415285433638837, "valid_loss": 1.850279060596548, "balanced_accuracy": 0.09090909090909091, "accuracy": 0.32955234744631806, "time_this_iter_s": 11.279796838760376, "done": false, "timesteps_total": null, "episodes_total": null, "training_iteration": 58, "trial_id": "a0875632", "experiment_id": "ba764abc1df047249af424415e270160", "date": "2022-07-12_18-14-33", "timestamp": 1657667673, "time_total_s": 755.5369455814362, "pid": 205749, "hostname": "desktop", "node_ip": "127.0.1.1", "config": {"n_layers": 2, "optimizer__lr": 3.056740793738313e-05, "n_head": 8, "n_hid": 64, "dropout": 0.048264643591270306, "numerical_passthrough": true}, "time_since_restore": 755.5369455814362, "timesteps_since_restore": 0, "iterations_since_restore": 58}
{"train_loss": 1.8401455173326988, "valid_loss": 1.849042548624821, "balanced_accuracy": 0.09090909090909091, "accuracy": 0.32955234744631806, "time_this_iter_s": 13.527835130691528, "done": false, "timesteps_total": null, "episodes_total": null, "training_iteration": 59, "trial_id": "a0875632", "experiment_id": "ba764abc1df047249af424415e270160", "date": "2022-07-12_18-14-46", "timestamp": 1657667686, "time_total_s": 769.0647807121277, "pid": 205749, "hostname": "desktop", "node_ip": "127.0.1.1", "config": {"n_layers": 2, "optimizer__lr": 3.056740793738313e-05, "n_head": 8, "n_hid": 64, "dropout": 0.048264643591270306, "numerical_passthrough": true}, "time_since_restore": 769.0647807121277, "timesteps_since_restore": 0, "iterations_since_restore": 59}
{"train_loss": 1.8388128846388454, "valid_loss": 1.847852413477603, "balanced_accuracy": 0.09090909090909091, "accuracy": 0.32955234744631806, "time_this_iter_s": 13.041259050369263, "done": false, "timesteps_total": null, "episodes_total": null, "training_iteration": 60, "trial_id": "a0875632", "experiment_id": "ba764abc1df047249af424415e270160", "date": "2022-07-12_18-14-59", "timestamp": 1657667699, "time_total_s": 782.106039762497, "pid": 205749, "hostname": "desktop", "node_ip": "127.0.1.1", "config": {"n_layers": 2, "optimizer__lr": 3.056740793738313e-05, "n_head": 8, "n_hid": 64, "dropout": 0.048264643591270306, "numerical_passthrough": true}, "time_since_restore": 782.106039762497, "timesteps_since_restore": 0, "iterations_since_restore": 60}
{"train_loss": 1.8374916527523775, "valid_loss": 1.8467057013445134, "balanced_accuracy": 0.09090909090909091, "accuracy": 0.32955234744631806, "time_this_iter_s": 13.246492624282837, "done": false, "timesteps_total": null, "episodes_total": null, "training_iteration": 61, "trial_id": "a0875632", "experiment_id": "ba764abc1df047249af424415e270160", "date": "2022-07-12_18-15-13", "timestamp": 1657667713, "time_total_s": 795.3525323867798, "pid": 205749, "hostname": "desktop", "node_ip": "127.0.1.1", "config": {"n_layers": 2, "optimizer__lr": 3.056740793738313e-05, "n_head": 8, "n_hid": 64, "dropout": 0.048264643591270306, "numerical_passthrough": true}, "time_since_restore": 795.3525323867798, "timesteps_since_restore": 0, "iterations_since_restore": 61}
{"train_loss": 1.836225508645685, "valid_loss": 1.845599501294649, "balanced_accuracy": 0.09090909090909091, "accuracy": 0.32955234744631806, "time_this_iter_s": 13.00370717048645, "done": false, "timesteps_total": null, "episodes_total": null, "training_iteration": 62, "trial_id": "a0875632", "experiment_id": "ba764abc1df047249af424415e270160", "date": "2022-07-12_18-15-26", "timestamp": 1657667726, "time_total_s": 808.3562395572662, "pid": 205749, "hostname": "desktop", "node_ip": "127.0.1.1", "config": {"n_layers": 2, "optimizer__lr": 3.056740793738313e-05, "n_head": 8, "n_hid": 64, "dropout": 0.048264643591270306, "numerical_passthrough": true}, "time_since_restore": 808.3562395572662, "timesteps_since_restore": 0, "iterations_since_restore": 62}
{"train_loss": 1.835044769845685, "valid_loss": 1.8445310553604286, "balanced_accuracy": 0.09157665168945196, "accuracy": 0.33094747058109913, "time_this_iter_s": 12.484098196029663, "done": false, "timesteps_total": null, "episodes_total": null, "training_iteration": 63, "trial_id": "a0875632", "experiment_id": "ba764abc1df047249af424415e270160", "date": "2022-07-12_18-15-38", "timestamp": 1657667738, "time_total_s": 820.8403377532959, "pid": 205749, "hostname": "desktop", "node_ip": "127.0.1.1", "config": {"n_layers": 2, "optimizer__lr": 3.056740793738313e-05, "n_head": 8, "n_hid": 64, "dropout": 0.048264643591270306, "numerical_passthrough": true}, "time_since_restore": 820.8403377532959, "timesteps_since_restore": 0, "iterations_since_restore": 63}
{"train_loss": 1.8339434176065181, "valid_loss": 1.843498195893814, "balanced_accuracy": 0.09289504048910119, "accuracy": 0.333677059323062, "time_this_iter_s": 14.927485942840576, "done": false, "timesteps_total": null, "episodes_total": null, "training_iteration": 64, "trial_id": "a0875632", "experiment_id": "ba764abc1df047249af424415e270160", "date": "2022-07-12_18-15-53", "timestamp": 1657667753, "time_total_s": 835.7678236961365, "pid": 205749, "hostname": "desktop", "node_ip": "127.0.1.1", "config": {"n_layers": 2, "optimizer__lr": 3.056740793738313e-05, "n_head": 8, "n_hid": 64, "dropout": 0.048264643591270306, "numerical_passthrough": true}, "time_since_restore": 835.7678236961365, "timesteps_since_restore": 0, "iterations_since_restore": 64}
{"train_loss": 1.8326475040203707, "valid_loss": 1.8424991364330396, "balanced_accuracy": 0.0943084013851423, "accuracy": 0.33670993570302077, "time_this_iter_s": 13.699491262435913, "done": false, "timesteps_total": null, "episodes_total": null, "training_iteration": 65, "trial_id": "a0875632", "experiment_id": "ba764abc1df047249af424415e270160", "date": "2022-07-12_18-16-07", "timestamp": 1657667767, "time_total_s": 849.4673149585724, "pid": 205749, "hostname": "desktop", "node_ip": "127.0.1.1", "config": {"n_layers": 2, "optimizer__lr": 3.056740793738313e-05, "n_head": 8, "n_hid": 64, "dropout": 0.048264643591270306, "numerical_passthrough": true}, "time_since_restore": 849.4673149585724, "timesteps_since_restore": 0, "iterations_since_restore": 65}
{"train_loss": 1.8316388381101634, "valid_loss": 1.8415318894672636, "balanced_accuracy": 0.09576111162431106, "accuracy": 0.33980346961057867, "time_this_iter_s": 12.199186563491821, "done": false, "timesteps_total": null, "episodes_total": null, "training_iteration": 66, "trial_id": "a0875632", "experiment_id": "ba764abc1df047249af424415e270160", "date": "2022-07-12_18-16-19", "timestamp": 1657667779, "time_total_s": 861.6665015220642, "pid": 205749, "hostname": "desktop", "node_ip": "127.0.1.1", "config": {"n_layers": 2, "optimizer__lr": 3.056740793738313e-05, "n_head": 8, "n_hid": 64, "dropout": 0.048264643591270306, "numerical_passthrough": true}, "time_since_restore": 861.6665015220642, "timesteps_since_restore": 0, "iterations_since_restore": 66}
{"train_loss": 1.830546118139165, "valid_loss": 1.8405940099261737, "balanced_accuracy": 0.09654626108311874, "accuracy": 0.34150188038335555, "time_this_iter_s": 13.93739104270935, "done": false, "timesteps_total": null, "episodes_total": null, "training_iteration": 67, "trial_id": "a0875632", "experiment_id": "ba764abc1df047249af424415e270160", "date": "2022-07-12_18-16-33", "timestamp": 1657667793, "time_total_s": 875.6038925647736, "pid": 205749, "hostname": "desktop", "node_ip": "127.0.1.1", "config": {"n_layers": 2, "optimizer__lr": 3.056740793738313e-05, "n_head": 8, "n_hid": 64, "dropout": 0.048264643591270306, "numerical_passthrough": true}, "time_since_restore": 875.6038925647736, "timesteps_since_restore": 0, "iterations_since_restore": 67}
{"train_loss": 1.8295436081891499, "valid_loss": 1.8396845648737914, "balanced_accuracy": 0.09956351141260954, "accuracy": 0.34720368797767803, "time_this_iter_s": 14.17153549194336, "done": false, "timesteps_total": null, "episodes_total": null, "training_iteration": 68, "trial_id": "a0875632", "experiment_id": "ba764abc1df047249af424415e270160", "date": "2022-07-12_18-16-47", "timestamp": 1657667807, "time_total_s": 889.7754280567169, "pid": 205749, "hostname": "desktop", "node_ip": "127.0.1.1", "config": {"n_layers": 2, "optimizer__lr": 3.056740793738313e-05, "n_head": 8, "n_hid": 64, "dropout": 0.048264643591270306, "numerical_passthrough": true}, "time_since_restore": 889.7754280567169, "timesteps_since_restore": 0, "iterations_since_restore": 68}
{"train_loss": 1.828590487112022, "valid_loss": 1.8388014467078102, "balanced_accuracy": 0.10270132927073349, "accuracy": 0.353087468154798, "time_this_iter_s": 14.037961959838867, "done": false, "timesteps_total": null, "episodes_total": null, "training_iteration": 69, "trial_id": "a0875632", "experiment_id": "ba764abc1df047249af424415e270160", "date": "2022-07-12_18-17-01", "timestamp": 1657667821, "time_total_s": 903.8133900165558, "pid": 205749, "hostname": "desktop", "node_ip": "127.0.1.1", "config": {"n_layers": 2, "optimizer__lr": 3.056740793738313e-05, "n_head": 8, "n_hid": 64, "dropout": 0.048264643591270306, "numerical_passthrough": true}, "time_since_restore": 903.8133900165558, "timesteps_since_restore": 0, "iterations_since_restore": 69}
{"train_loss": 1.8275942684564865, "valid_loss": 1.837943703041021, "balanced_accuracy": 0.104965476772608, "accuracy": 0.3573334950867403, "time_this_iter_s": 13.099424839019775, "done": false, "timesteps_total": null, "episodes_total": null, "training_iteration": 70, "trial_id": "a0875632", "experiment_id": "ba764abc1df047249af424415e270160", "date": "2022-07-12_18-17-14", "timestamp": 1657667834, "time_total_s": 916.9128148555756, "pid": 205749, "hostname": "desktop", "node_ip": "127.0.1.1", "config": {"n_layers": 2, "optimizer__lr": 3.056740793738313e-05, "n_head": 8, "n_hid": 64, "dropout": 0.048264643591270306, "numerical_passthrough": true}, "time_since_restore": 916.9128148555756, "timesteps_since_restore": 0, "iterations_since_restore": 70}
{"train_loss": 1.8267127750105872, "valid_loss": 1.8371095157401387, "balanced_accuracy": 0.10672254774385052, "accuracy": 0.3608516316874924, "time_this_iter_s": 12.65583324432373, "done": false, "timesteps_total": null, "episodes_total": null, "training_iteration": 71, "trial_id": "a0875632", "experiment_id": "ba764abc1df047249af424415e270160", "date": "2022-07-12_18-17-27", "timestamp": 1657667847, "time_total_s": 929.5686480998993, "pid": 205749, "hostname": "desktop", "node_ip": "127.0.1.1", "config": {"n_layers": 2, "optimizer__lr": 3.056740793738313e-05, "n_head": 8, "n_hid": 64, "dropout": 0.048264643591270306, "numerical_passthrough": true}, "time_since_restore": 929.5686480998993, "timesteps_since_restore": 0, "iterations_since_restore": 71}
{"train_loss": 1.825780783479948, "valid_loss": 1.8362983595062399, "balanced_accuracy": 0.10829101953387249, "accuracy": 0.363823850539852, "time_this_iter_s": 13.395143032073975, "done": false, "timesteps_total": null, "episodes_total": null, "training_iteration": 72, "trial_id": "a0875632", "experiment_id": "ba764abc1df047249af424415e270160", "date": "2022-07-12_18-17-40", "timestamp": 1657667860, "time_total_s": 942.9637911319733, "pid": 205749, "hostname": "desktop", "node_ip": "127.0.1.1", "config": {"n_layers": 2, "optimizer__lr": 3.056740793738313e-05, "n_head": 8, "n_hid": 64, "dropout": 0.048264643591270306, "numerical_passthrough": true}, "time_since_restore": 942.9637911319733, "timesteps_since_restore": 0, "iterations_since_restore": 72}
{"train_loss": 1.82482774179855, "valid_loss": 1.8355084285854093, "balanced_accuracy": 0.10958379013618659, "accuracy": 0.3661894941162198, "time_this_iter_s": 13.769191980361938, "done": false, "timesteps_total": null, "episodes_total": null, "training_iteration": 73, "trial_id": "a0875632", "experiment_id": "ba764abc1df047249af424415e270160", "date": "2022-07-12_18-17-54", "timestamp": 1657667874, "time_total_s": 956.7329831123352, "pid": 205749, "hostname": "desktop", "node_ip": "127.0.1.1", "config": {"n_layers": 2, "optimizer__lr": 3.056740793738313e-05, "n_head": 8, "n_hid": 64, "dropout": 0.048264643591270306, "numerical_passthrough": true}, "time_since_restore": 956.7329831123352, "timesteps_since_restore": 0, "iterations_since_restore": 73}
{"train_loss": 1.8239138578451708, "valid_loss": 1.8347390341003817, "balanced_accuracy": 0.11049945902054463, "accuracy": 0.3677665898337984, "time_this_iter_s": 12.791923999786377, "done": false, "timesteps_total": null, "episodes_total": null, "training_iteration": 74, "trial_id": "a0875632", "experiment_id": "ba764abc1df047249af424415e270160", "date": "2022-07-12_18-18-07", "timestamp": 1657667887, "time_total_s": 969.5249071121216, "pid": 205749, "hostname": "desktop", "node_ip": "127.0.1.1", "config": {"n_layers": 2, "optimizer__lr": 3.056740793738313e-05, "n_head": 8, "n_hid": 64, "dropout": 0.048264643591270306, "numerical_passthrough": true}, "time_since_restore": 969.5249071121216, "timesteps_since_restore": 0, "iterations_since_restore": 74}
{"train_loss": 1.8231722094199039, "valid_loss": 1.833988404166969, "balanced_accuracy": 0.11189733552259097, "accuracy": 0.3704961785757612, "time_this_iter_s": 12.626506328582764, "done": false, "timesteps_total": null, "episodes_total": null, "training_iteration": 75, "trial_id": "a0875632", "experiment_id": "ba764abc1df047249af424415e270160", "date": "2022-07-12_18-18-19", "timestamp": 1657667899, "time_total_s": 982.1514134407043, "pid": 205749, "hostname": "desktop", "node_ip": "127.0.1.1", "config": {"n_layers": 2, "optimizer__lr": 3.056740793738313e-05, "n_head": 8, "n_hid": 64, "dropout": 0.048264643591270306, "numerical_passthrough": true}, "time_since_restore": 982.1514134407043, "timesteps_since_restore": 0, "iterations_since_restore": 75}
{"train_loss": 1.8223494462968075, "valid_loss": 1.833256127561569, "balanced_accuracy": 0.1126823030749755, "accuracy": 0.3718306441829431, "time_this_iter_s": 12.453049898147583, "done": false, "timesteps_total": null, "episodes_total": null, "training_iteration": 76, "trial_id": "a0875632", "experiment_id": "ba764abc1df047249af424415e270160", "date": "2022-07-12_18-18-32", "timestamp": 1657667912, "time_total_s": 994.6044633388519, "pid": 205749, "hostname": "desktop", "node_ip": "127.0.1.1", "config": {"n_layers": 2, "optimizer__lr": 3.056740793738313e-05, "n_head": 8, "n_hid": 64, "dropout": 0.048264643591270306, "numerical_passthrough": true}, "time_since_restore": 994.6044633388519, "timesteps_since_restore": 0, "iterations_since_restore": 76}
{"train_loss": 1.8214578315584922, "valid_loss": 1.8325415935589244, "balanced_accuracy": 0.11377878631258766, "accuracy": 0.3737716850661167, "time_this_iter_s": 12.83862018585205, "done": false, "timesteps_total": null, "episodes_total": null, "training_iteration": 77, "trial_id": "a0875632", "experiment_id": "ba764abc1df047249af424415e270160", "date": "2022-07-12_18-18-45", "timestamp": 1657667925, "time_total_s": 1007.443083524704, "pid": 205749, "hostname": "desktop", "node_ip": "127.0.1.1", "config": {"n_layers": 2, "optimizer__lr": 3.056740793738313e-05, "n_head": 8, "n_hid": 64, "dropout": 0.048264643591270306, "numerical_passthrough": true}, "time_since_restore": 1007.443083524704, "timesteps_since_restore": 0, "iterations_since_restore": 77}
{"train_loss": 1.8208203334246071, "valid_loss": 1.831844116231994, "balanced_accuracy": 0.1147511671759588, "accuracy": 0.3754700958388936, "time_this_iter_s": 13.128396034240723, "done": false, "timesteps_total": null, "episodes_total": null, "training_iteration": 78, "trial_id": "a0875632", "experiment_id": "ba764abc1df047249af424415e270160", "date": "2022-07-12_18-18-58", "timestamp": 1657667938, "time_total_s": 1020.5714795589447, "pid": 205749, "hostname": "desktop", "node_ip": "127.0.1.1", "config": {"n_layers": 2, "optimizer__lr": 3.056740793738313e-05, "n_head": 8, "n_hid": 64, "dropout": 0.048264643591270306, "numerical_passthrough": true}, "time_since_restore": 1020.5714795589447, "timesteps_since_restore": 0, "iterations_since_restore": 78}
{"train_loss": 1.8199541149506158, "valid_loss": 1.8311621598735763, "balanced_accuracy": 0.11561083921805441, "accuracy": 0.376986534028873, "time_this_iter_s": 12.575222492218018, "done": false, "timesteps_total": null, "episodes_total": null, "training_iteration": 79, "trial_id": "a0875632", "experiment_id": "ba764abc1df047249af424415e270160", "date": "2022-07-12_18-19-10", "timestamp": 1657667950, "time_total_s": 1033.1467020511627, "pid": 205749, "hostname": "desktop", "node_ip": "127.0.1.1", "config": {"n_layers": 2, "optimizer__lr": 3.056740793738313e-05, "n_head": 8, "n_hid": 64, "dropout": 0.048264643591270306, "numerical_passthrough": true}, "time_since_restore": 1033.1467020511627, "timesteps_since_restore": 0, "iterations_since_restore": 79}
{"train_loss": 1.8191710706620805, "valid_loss": 1.8304956812860318, "balanced_accuracy": 0.11633212174469511, "accuracy": 0.378381657163654, "time_this_iter_s": 12.464520692825317, "done": false, "timesteps_total": null, "episodes_total": null, "training_iteration": 80, "trial_id": "a0875632", "experiment_id": "ba764abc1df047249af424415e270160", "date": "2022-07-12_18-19-23", "timestamp": 1657667963, "time_total_s": 1045.611222743988, "pid": 205749, "hostname": "desktop", "node_ip": "127.0.1.1", "config": {"n_layers": 2, "optimizer__lr": 3.056740793738313e-05, "n_head": 8, "n_hid": 64, "dropout": 0.048264643591270306, "numerical_passthrough": true}, "time_since_restore": 1045.611222743988, "timesteps_since_restore": 0, "iterations_since_restore": 80}
{"train_loss": 1.8184310075338064, "valid_loss": 1.829843630753688, "balanced_accuracy": 0.11725267048622427, "accuracy": 0.3800800679364309, "time_this_iter_s": 13.28011441230774, "done": false, "timesteps_total": null, "episodes_total": null, "training_iteration": 81, "trial_id": "a0875632", "experiment_id": "ba764abc1df047249af424415e270160", "date": "2022-07-12_18-19-36", "timestamp": 1657667976, "time_total_s": 1058.8913371562958, "pid": 205749, "hostname": "desktop", "node_ip": "127.0.1.1", "config": {"n_layers": 2, "optimizer__lr": 3.056740793738313e-05, "n_head": 8, "n_hid": 64, "dropout": 0.048264643591270306, "numerical_passthrough": true}, "time_since_restore": 1058.8913371562958, "timesteps_since_restore": 0, "iterations_since_restore": 81}
{"train_loss": 1.8177512808793612, "valid_loss": 1.829205584456645, "balanced_accuracy": 0.1180312096047525, "accuracy": 0.3815358485988111, "time_this_iter_s": 12.131038427352905, "done": false, "timesteps_total": null, "episodes_total": null, "training_iteration": 82, "trial_id": "a0875632", "experiment_id": "ba764abc1df047249af424415e270160", "date": "2022-07-12_18-19-48", "timestamp": 1657667988, "time_total_s": 1071.0223755836487, "pid": 205749, "hostname": "desktop", "node_ip": "127.0.1.1", "config": {"n_layers": 2, "optimizer__lr": 3.056740793738313e-05, "n_head": 8, "n_hid": 64, "dropout": 0.048264643591270306, "numerical_passthrough": true}, "time_since_restore": 1071.0223755836487, "timesteps_since_restore": 0, "iterations_since_restore": 82}
{"train_loss": 1.817036311386078, "valid_loss": 1.8285806478696816, "balanced_accuracy": 0.1184660272655324, "accuracy": 0.3822637389300012, "time_this_iter_s": 12.460673332214355, "done": false, "timesteps_total": null, "episodes_total": null, "training_iteration": 83, "trial_id": "a0875632", "experiment_id": "ba764abc1df047249af424415e270160", "date": "2022-07-12_18-20-01", "timestamp": 1657668001, "time_total_s": 1083.483048915863, "pid": 205749, "hostname": "desktop", "node_ip": "127.0.1.1", "config": {"n_layers": 2, "optimizer__lr": 3.056740793738313e-05, "n_head": 8, "n_hid": 64, "dropout": 0.048264643591270306, "numerical_passthrough": true}, "time_since_restore": 1083.483048915863, "timesteps_since_restore": 0, "iterations_since_restore": 83}
{"train_loss": 1.816369756034866, "valid_loss": 1.8279684975817412, "balanced_accuracy": 0.11905189912690471, "accuracy": 0.38341623195438557, "time_this_iter_s": 13.702257633209229, "done": false, "timesteps_total": null, "episodes_total": null, "training_iteration": 84, "trial_id": "a0875632", "experiment_id": "ba764abc1df047249af424415e270160", "date": "2022-07-12_18-20-14", "timestamp": 1657668014, "time_total_s": 1097.1853065490723, "pid": 205749, "hostname": "desktop", "node_ip": "127.0.1.1", "config": {"n_layers": 2, "optimizer__lr": 3.056740793738313e-05, "n_head": 8, "n_hid": 64, "dropout": 0.048264643591270306, "numerical_passthrough": true}, "time_since_restore": 1097.1853065490723, "timesteps_since_restore": 0, "iterations_since_restore": 84}
{"train_loss": 1.815692349442229, "valid_loss": 1.8273686350917666, "balanced_accuracy": 0.11939120007841825, "accuracy": 0.38390149217517894, "time_this_iter_s": 13.243727922439575, "done": false, "timesteps_total": null, "episodes_total": null, "training_iteration": 85, "trial_id": "a0875632", "experiment_id": "ba764abc1df047249af424415e270160", "date": "2022-07-12_18-20-28", "timestamp": 1657668028, "time_total_s": 1110.4290344715118, "pid": 205749, "hostname": "desktop", "node_ip": "127.0.1.1", "config": {"n_layers": 2, "optimizer__lr": 3.056740793738313e-05, "n_head": 8, "n_hid": 64, "dropout": 0.048264643591270306, "numerical_passthrough": true}, "time_since_restore": 1110.4290344715118, "timesteps_since_restore": 0, "iterations_since_restore": 85}
{"train_loss": 1.8150397302687031, "valid_loss": 1.8267804979193374, "balanced_accuracy": 0.11998358563558496, "accuracy": 0.3849933276719641, "time_this_iter_s": 12.681118726730347, "done": false, "timesteps_total": null, "episodes_total": null, "training_iteration": 86, "trial_id": "a0875632", "experiment_id": "ba764abc1df047249af424415e270160", "date": "2022-07-12_18-20-40", "timestamp": 1657668040, "time_total_s": 1123.1101531982422, "pid": 205749, "hostname": "desktop", "node_ip": "127.0.1.1", "config": {"n_layers": 2, "optimizer__lr": 3.056740793738313e-05, "n_head": 8, "n_hid": 64, "dropout": 0.048264643591270306, "numerical_passthrough": true}, "time_since_restore": 1123.1101531982422, "timesteps_since_restore": 0, "iterations_since_restore": 86}
{"train_loss": 1.8144145900584476, "valid_loss": 1.826203648708232, "balanced_accuracy": 0.12065059042052466, "accuracy": 0.3862064782239476, "time_this_iter_s": 14.23674750328064, "done": false, "timesteps_total": null, "episodes_total": null, "training_iteration": 87, "trial_id": "a0875632", "experiment_id": "ba764abc1df047249af424415e270160", "date": "2022-07-12_18-20-55", "timestamp": 1657668055, "time_total_s": 1137.3469007015228, "pid": 205749, "hostname": "desktop", "node_ip": "127.0.1.1", "config": {"n_layers": 2, "optimizer__lr": 3.056740793738313e-05, "n_head": 8, "n_hid": 64, "dropout": 0.048264643591270306, "numerical_passthrough": true}, "time_since_restore": 1137.3469007015228, "timesteps_since_restore": 0, "iterations_since_restore": 87}
{"train_loss": 1.813777449812745, "valid_loss": 1.8256377094537906, "balanced_accuracy": 0.1212370068947714, "accuracy": 0.38729831372073276, "time_this_iter_s": 13.306195497512817, "done": false, "timesteps_total": null, "episodes_total": null, "training_iteration": 88, "trial_id": "a0875632", "experiment_id": "ba764abc1df047249af424415e270160", "date": "2022-07-12_18-21-08", "timestamp": 1657668068, "time_total_s": 1150.6530961990356, "pid": 205749, "hostname": "desktop", "node_ip": "127.0.1.1", "config": {"n_layers": 2, "optimizer__lr": 3.056740793738313e-05, "n_head": 8, "n_hid": 64, "dropout": 0.048264643591270306, "numerical_passthrough": true}, "time_since_restore": 1150.6530961990356, "timesteps_since_restore": 0, "iterations_since_restore": 88}
{"train_loss": 1.813076869530049, "valid_loss": 1.825082495824871, "balanced_accuracy": 0.12187588536567272, "accuracy": 0.3883901492175179, "time_this_iter_s": 12.903055191040039, "done": false, "timesteps_total": null, "episodes_total": null, "training_iteration": 89, "trial_id": "a0875632", "experiment_id": "ba764abc1df047249af424415e270160", "date": "2022-07-12_18-21-21", "timestamp": 1657668081, "time_total_s": 1163.5561513900757, "pid": 205749, "hostname": "desktop", "node_ip": "127.0.1.1", "config": {"n_layers": 2, "optimizer__lr": 3.056740793738313e-05, "n_head": 8, "n_hid": 64, "dropout": 0.048264643591270306, "numerical_passthrough": true}, "time_since_restore": 1163.5561513900757, "timesteps_since_restore": 0, "iterations_since_restore": 89}
{"train_loss": 1.8124929755893593, "valid_loss": 1.8245370169367356, "balanced_accuracy": 0.12284401624668528, "accuracy": 0.38996724493509644, "time_this_iter_s": 10.466747999191284, "done": false, "timesteps_total": null, "episodes_total": null, "training_iteration": 90, "trial_id": "a0875632", "experiment_id": "ba764abc1df047249af424415e270160", "date": "2022-07-12_18-21-31", "timestamp": 1657668091, "time_total_s": 1174.022899389267, "pid": 205749, "hostname": "desktop", "node_ip": "127.0.1.1", "config": {"n_layers": 2, "optimizer__lr": 3.056740793738313e-05, "n_head": 8, "n_hid": 64, "dropout": 0.048264643591270306, "numerical_passthrough": true}, "time_since_restore": 1174.022899389267, "timesteps_since_restore": 0, "iterations_since_restore": 90}
{"train_loss": 1.8119905625647255, "valid_loss": 1.8240010529543234, "balanced_accuracy": 0.1238391842159874, "accuracy": 0.3917869707630717, "time_this_iter_s": 13.420463800430298, "done": false, "timesteps_total": null, "episodes_total": null, "training_iteration": 91, "trial_id": "a0875632", "experiment_id": "ba764abc1df047249af424415e270160", "date": "2022-07-12_18-21-45", "timestamp": 1657668105, "time_total_s": 1187.4433631896973, "pid": 205749, "hostname": "desktop", "node_ip": "127.0.1.1", "config": {"n_layers": 2, "optimizer__lr": 3.056740793738313e-05, "n_head": 8, "n_hid": 64, "dropout": 0.048264643591270306, "numerical_passthrough": true}, "time_since_restore": 1187.4433631896973, "timesteps_since_restore": 0, "iterations_since_restore": 91}
{"train_loss": 1.8112937670721239, "valid_loss": 1.8234746358239302, "balanced_accuracy": 0.12435513480033467, "accuracy": 0.39257551862186096, "time_this_iter_s": 12.903783559799194, "done": false, "timesteps_total": null, "episodes_total": null, "training_iteration": 92, "trial_id": "a0875632", "experiment_id": "ba764abc1df047249af424415e270160", "date": "2022-07-12_18-21-58", "timestamp": 1657668118, "time_total_s": 1200.3471467494965, "pid": 205749, "hostname": "desktop", "node_ip": "127.0.1.1", "config": {"n_layers": 2, "optimizer__lr": 3.056740793738313e-05, "n_head": 8, "n_hid": 64, "dropout": 0.048264643591270306, "numerical_passthrough": true}, "time_since_restore": 1200.3471467494965, "timesteps_since_restore": 0, "iterations_since_restore": 92}
{"train_loss": 1.8107085455740943, "valid_loss": 1.8229572021540372, "balanced_accuracy": 0.12499409853317407, "accuracy": 0.3937280116462453, "time_this_iter_s": 13.725205183029175, "done": false, "timesteps_total": null, "episodes_total": null, "training_iteration": 93, "trial_id": "a0875632", "experiment_id": "ba764abc1df047249af424415e270160", "date": "2022-07-12_18-22-11", "timestamp": 1657668131, "time_total_s": 1214.0723519325256, "pid": 205749, "hostname": "desktop", "node_ip": "127.0.1.1", "config": {"n_layers": 2, "optimizer__lr": 3.056740793738313e-05, "n_head": 8, "n_hid": 64, "dropout": 0.048264643591270306, "numerical_passthrough": true}, "time_since_restore": 1214.0723519325256, "timesteps_since_restore": 0, "iterations_since_restore": 93}
{"train_loss": 1.8102518013057873, "valid_loss": 1.822448541596577, "balanced_accuracy": 0.12572487360579568, "accuracy": 0.3949411621982288, "time_this_iter_s": 12.221667528152466, "done": false, "timesteps_total": null, "episodes_total": null, "training_iteration": 94, "trial_id": "a0875632", "experiment_id": "ba764abc1df047249af424415e270160", "date": "2022-07-12_18-22-24", "timestamp": 1657668144, "time_total_s": 1226.294019460678, "pid": 205749, "hostname": "desktop", "node_ip": "127.0.1.1", "config": {"n_layers": 2, "optimizer__lr": 3.056740793738313e-05, "n_head": 8, "n_hid": 64, "dropout": 0.048264643591270306, "numerical_passthrough": true}, "time_since_restore": 1226.294019460678, "timesteps_since_restore": 0, "iterations_since_restore": 94}
{"train_loss": 1.809716462380357, "valid_loss": 1.8219482357114694, "balanced_accuracy": 0.12655650459579101, "accuracy": 0.396396942860609, "time_this_iter_s": 13.135631084442139, "done": false, "timesteps_total": null, "episodes_total": null, "training_iteration": 95, "trial_id": "a0875632", "experiment_id": "ba764abc1df047249af424415e270160", "date": "2022-07-12_18-22-37", "timestamp": 1657668157, "time_total_s": 1239.4296505451202, "pid": 205749, "hostname": "desktop", "node_ip": "127.0.1.1", "config": {"n_layers": 2, "optimizer__lr": 3.056740793738313e-05, "n_head": 8, "n_hid": 64, "dropout": 0.048264643591270306, "numerical_passthrough": true}, "time_since_restore": 1239.4296505451202, "timesteps_since_restore": 0, "iterations_since_restore": 95}
{"train_loss": 1.8090424609968099, "valid_loss": 1.8214562047125138, "balanced_accuracy": 0.12730275267986044, "accuracy": 0.39767075094019166, "time_this_iter_s": 12.711955308914185, "done": false, "timesteps_total": null, "episodes_total": null, "training_iteration": 96, "trial_id": "a0875632", "experiment_id": "ba764abc1df047249af424415e270160", "date": "2022-07-12_18-22-49", "timestamp": 1657668169, "time_total_s": 1252.1416058540344, "pid": 205749, "hostname": "desktop", "node_ip": "127.0.1.1", "config": {"n_layers": 2, "optimizer__lr": 3.056740793738313e-05, "n_head": 8, "n_hid": 64, "dropout": 0.048264643591270306, "numerical_passthrough": true}, "time_since_restore": 1252.1416058540344, "timesteps_since_restore": 0, "iterations_since_restore": 96}
{"train_loss": 1.8085223822921686, "valid_loss": 1.8209718731903675, "balanced_accuracy": 0.12776624126755315, "accuracy": 0.39845929879898095, "time_this_iter_s": 13.08389925956726, "done": false, "timesteps_total": null, "episodes_total": null, "training_iteration": 97, "trial_id": "a0875632", "experiment_id": "ba764abc1df047249af424415e270160", "date": "2022-07-12_18-23-03", "timestamp": 1657668183, "time_total_s": 1265.2255051136017, "pid": 205749, "hostname": "desktop", "node_ip": "127.0.1.1", "config": {"n_layers": 2, "optimizer__lr": 3.056740793738313e-05, "n_head": 8, "n_hid": 64, "dropout": 0.048264643591270306, "numerical_passthrough": true}, "time_since_restore": 1265.2255051136017, "timesteps_since_restore": 0, "iterations_since_restore": 97}
{"train_loss": 1.808121155509523, "valid_loss": 1.8204951285303586, "balanced_accuracy": 0.1280597644420828, "accuracy": 0.39900521654737353, "time_this_iter_s": 11.818816900253296, "done": false, "timesteps_total": null, "episodes_total": null, "training_iteration": 98, "trial_id": "a0875632", "experiment_id": "ba764abc1df047249af424415e270160", "date": "2022-07-12_18-23-14", "timestamp": 1657668194, "time_total_s": 1277.044322013855, "pid": 205749, "hostname": "desktop", "node_ip": "127.0.1.1", "config": {"n_layers": 2, "optimizer__lr": 3.056740793738313e-05, "n_head": 8, "n_hid": 64, "dropout": 0.048264643591270306, "numerical_passthrough": true}, "time_since_restore": 1277.044322013855, "timesteps_since_restore": 0, "iterations_since_restore": 98}
{"train_loss": 1.8074776976631781, "valid_loss": 1.8200260905925616, "balanced_accuracy": 0.12857399592586863, "accuracy": 0.3999150794613612, "time_this_iter_s": 14.455421447753906, "done": false, "timesteps_total": null, "episodes_total": null, "training_iteration": 99, "trial_id": "a0875632", "experiment_id": "ba764abc1df047249af424415e270160", "date": "2022-07-12_18-23-29", "timestamp": 1657668209, "time_total_s": 1291.499743461609, "pid": 205749, "hostname": "desktop", "node_ip": "127.0.1.1", "config": {"n_layers": 2, "optimizer__lr": 3.056740793738313e-05, "n_head": 8, "n_hid": 64, "dropout": 0.048264643591270306, "numerical_passthrough": true}, "time_since_restore": 1291.499743461609, "timesteps_since_restore": 0, "iterations_since_restore": 99}
{"train_loss": 1.8069750218661567, "valid_loss": 1.8195638787785477, "balanced_accuracy": 0.12876006422529204, "accuracy": 0.40021836709935704, "time_this_iter_s": 12.088783502578735, "done": true, "timesteps_total": null, "episodes_total": null, "training_iteration": 100, "trial_id": "a0875632", "experiment_id": "ba764abc1df047249af424415e270160", "date": "2022-07-12_18-23-41", "timestamp": 1657668221, "time_total_s": 1303.5885269641876, "pid": 205749, "hostname": "desktop", "node_ip": "127.0.1.1", "config": {"n_layers": 2, "optimizer__lr": 3.056740793738313e-05, "n_head": 8, "n_hid": 64, "dropout": 0.048264643591270306, "numerical_passthrough": true}, "time_since_restore": 1303.5885269641876, "timesteps_since_restore": 0, "iterations_since_restore": 100}
